memcached_clients/VERSION
memcached_clients/__init__.py
memcached_clients/base.py
memcached_clients/django_backend.py
memcached_clients/restclient.py
memcached_clients/test.py
memcached_clients/tests/__init__.py
memcached_clients/tests/test_base.py
memcached_clients/tests/test_django_backend.py
memcached_clients/tests/test_restclient.py
memcached_clients/tests/django/__init__.py
memcached_clients/tests/django/apps.py
memcached_clients/tests/django/settings.py
uw_memcached_clients-1.1.2.dist-info/licenses/LICENSE
uw_memcached_clients-1.1.2.dist-info/METADATA
uw_memcached_clients-1.1.2.dist-info/WHEEL
uw_memcached_clients-1.1.2.dist-info/top_level.txt
uw_memcached_clients-1.1.2.dist-info/RECORD
