Metadata-Version: 2.4
Name: uw-memcached-clients
Version: 1.1.2
Summary: Memcached clients
Home-page: https://github.com/uw-it-aca/uw-memcached-clients
Author: UW-IT Student & Educational Technology Services
Author-email: aca-it@uw.edu
License: Apache License, Version 2.0
Classifier: Intended Audience :: Developers
Classifier: License :: OSI Approved :: Apache Software License
Classifier: Operating System :: OS Independent
Classifier: Programming Language :: Python
License-File: LICENSE
Requires-Dist: pymemcache~=4.0
Requires-Dist: commonconf
Requires-Dist: mock
Dynamic: author
Dynamic: author-email
Dynamic: classifier
Dynamic: description
Dynamic: home-page
Dynamic: license
Dynamic: license-file
Dynamic: requires-dist
Dynamic: summary
